ch4/src/sillyfunction.v


module sillyfunction(a, b, c, y);

input wire a;
input wire b;
input wire c;
output wire y;

assign y = ~a & ~b & ~c | 
	a & ~b & ~c |
	a & ~b & c;

endmodule

ch4/src/sillyfunction_tb.v

module top;

	reg a, b, c;
	wire y;

	sillyfunction U0 (
		.a(a),
		.b(b),
		.c(c),
		.y(y)
	);

	initial
	begin
		a=0;b=0;c=0;
	end

	initial
	begin
		$dumpfile("outputs/simple.vcd");
		$dumpvars(0, top);
		$display("\ttime\t\ta,\tb,\tc,\ty"); 
		$monitor("%d,\t%b,\t%b,\t%b,\t%b",$time,a,b,c,y); 
	end

	always
	begin
		#5 a=1;b=0;c=0;
		#5 a=0;b=1;c=0;
		#5 a=0;b=0;c=1;
		#5 a=1;b=1;c=0;
		#5 a=1;b=0;c=1;
		#5 a=0;b=1;c=1;
		#5 a=0;b=0;c=1;
		#5 a=0;b=0;c=1;
	end

	initial
		#45 $finish;

endmodule

ch4/src/simple.vcd
$date
	Sat Nov 19 23:49:45 2016
$end
$version
	Icarus Verilog
$end
$timescale
	1s
$end
$scope module top $end
$var wire 1 ! y $end
$var reg 1 " a $end
$var reg 1 # b $end
$var reg 1 $ c $end
$scope module U0 $end
$var wire 1 " a $end
$var wire 1 # b $end
$var wire 1 $ c $end
$var wire 1 ! y $end
$upscope $end
$upscope $end
$enddefinitions $end
#0
$dumpvars
0$
0#
0"
1!
$end
#5
1"
#10
0!
1#
0"
#15
1$
0#
#20
0!
0$
1#
1"
#25
1!
1$
0#
#30
0!
1#
0"
#35
0#
#45
1!
0$
1"
